offlinerl/__init__.py
offlinerl/algo/__init__.py
offlinerl/algo/base.py
offlinerl/algo/dynamics_model/__init__.py
offlinerl/algo/dynamics_model/bc_model.py
offlinerl/algo/modelbase/__init__.py
offlinerl/algo/modelbase/bremen.py
offlinerl/algo/modelbase/combo.py
offlinerl/algo/modelbase/maple.py
offlinerl/algo/modelbase/maple_new.py
offlinerl/algo/modelbase/mobile.py
offlinerl/algo/modelbase/model_base.py
offlinerl/algo/modelbase/moose.py
offlinerl/algo/modelbase/mopo.py
offlinerl/algo/modelbase/rambo.py
offlinerl/algo/modelfree/__init__.py
offlinerl/algo/modelfree/bc.py
offlinerl/algo/modelfree/bcq.py
offlinerl/algo/modelfree/bcqd.py
offlinerl/algo/modelfree/cql.py
offlinerl/algo/modelfree/crr.py
offlinerl/algo/modelfree/edac.py
offlinerl/algo/modelfree/mcq.py
offlinerl/algo/modelfree/plas.py
offlinerl/algo/modelfree/prdc.py
offlinerl/algo/modelfree/td3bc.py
offlinerl/algo/online/__init__.py
offlinerl/algo/online/bremen.py
offlinerl/config/__init__.py
offlinerl/config/algo/__init__.py
offlinerl/config/algo/bc_config.py
offlinerl/config/algo/bc_model_config.py
offlinerl/config/algo/bcq_config.py
offlinerl/config/algo/bcqd_config.py
offlinerl/config/algo/bremen_config.py
offlinerl/config/algo/combo_config.py
offlinerl/config/algo/cql_config.py
offlinerl/config/algo/crr_config.py
offlinerl/config/algo/edac_config.py
offlinerl/config/algo/maple_config.py
offlinerl/config/algo/maple_config_new.py
offlinerl/config/algo/mcq_config.py
offlinerl/config/algo/mobile_config.py
offlinerl/config/algo/moose_config.py
offlinerl/config/algo/mopo_config.py
offlinerl/config/algo/plas_config.py
offlinerl/config/algo/prdc_config.py
offlinerl/config/algo/rambo_config.py
offlinerl/config/algo/td3bc_config.py
offlinerl/data/__init__.py
offlinerl/data/d4rl.py
offlinerl/data/neorl.py
offlinerl/evaluation/__init__.py
offlinerl/evaluation/d4rl.py
offlinerl/evaluation/fqe.py
offlinerl/evaluation/gym.py
offlinerl/evaluation/neorl.py
offlinerl/utils/__init__.py
offlinerl/utils/config.py
offlinerl-0.0.2.dist-info/LICENSE
offlinerl-0.0.2.dist-info/METADATA
offlinerl-0.0.2.dist-info/WHEEL
offlinerl-0.0.2.dist-info/top_level.txt
offlinerl-0.0.2.dist-info/RECORD
