Metadata-Version: 2.1
Name: offlinerl
Version: 0.0.2
Summary: A Library for Offline RL(Batch RL)
Home-page: https://agit.ai/Polixir/OfflineRL
Author: SongyiGao
Author-email: songyigao@gmail.com
Requires-Python: >=3.7
License-File: LICENSE
Requires-Dist: aim
Requires-Dist: fire
Requires-Dist: loguru
Requires-Dist: gym
Requires-Dist: scikit-learn
Requires-Dist: gtimer
Requires-Dist: numpy
Requires-Dist: ray ==2.9
Requires-Dist: aioredis ==1.3.1
Requires-Dist: aiohttp ==3.7.4
